markable/__init__.py
markable/markable.py
markable-1.0.1.dist-info/LICENSE
markable-1.0.1.dist-info/METADATA
markable-1.0.1.dist-info/WHEEL
markable-1.0.1.dist-info/top_level.txt
markable-1.0.1.dist-info/RECORD
