Metadata-Version: 2.1
Name: markable
Version: 1.0.1
Summary: Print out colorful text.
Home-page: https://github.com/Ron-Chang/markable
Author: Ron Chang
Author-email: ron.hsien.chang@gmail.com
License: MIT
Platform: UNKNOWN
Requires-Python: >=3
